wiki3_ai/__init__.py
wiki3_ai/language_model.py
wiki3_ai-0.5.1.dist-info/METADATA
wiki3_ai-0.5.1.dist-info/WHEEL
wiki3_ai-0.5.1.dist-info/licenses/LICENSE
wiki3_ai-0.5.1.dist-info/RECORD
