Metadata-Version: 2.4
Name: wiki3-ai
Version: 0.5.1
Summary: Python wrapper for Chrome's built-in AI Prompt API
Project-URL: Homepage, https://github.com/fovi-llc/python-ai
Project-URL: Repository, https://github.com/fovi-llc/python-ai
Project-URL: Issues, https://github.com/fovi-llc/python-ai/issues
Author: jim@fovi.com
License:                                  Apache License
License-File: LICENSE
Classifier: Development Status :: 3 - Alpha
Classifier: Intended Audience :: Developers
Classifier: License :: OSI Approved :: Apache Software License
Classifier: Programming Language :: Python :: 3
Classifier: Programming Language :: Python :: 3.10
Classifier: Programming Language :: Python :: 3.11
Classifier: Programming Language :: Python :: 3.12
Classifier: Topic :: Scientific/Engineering :: Artificial Intelligence
Requires-Python: >=3.10
Requires-Dist: anywidget>=0.9.0
Requires-Dist: traitlets>=5.0.0
Provides-Extra: dev
Requires-Dist: black>=23.0.0; extra == 'dev'
Requires-Dist: pytest-asyncio>=0.21.0; extra == 'dev'
Requires-Dist: pytest>=7.0.0; extra == 'dev'
Requires-Dist: ruff>=0.1.0; extra == 'dev'
